{
  "index": 21,
  "blueprint": {
    "item": "blueprint",
    "label": "Bot-run bot maker",
    "description": "In progress.  The idea is we'll use requester chests to make a logistics bot-run bot maker that makes 60 bots/min of both types.\nIncludes steel smelting.",
    "shift_x": -293,
    "shift_y": 387,
    "version": 562949956501504,
    "entities": [
      {
        "name": "assembling-machine-1",
        "recipe": "copper-cable",
        "recipe_quality": "normal",
        "position": {"x": 22.5, "y": 9.5}
      },
      {
        "name": "assembling-machine-1",
        "recipe": "copper-cable",
        "recipe_quality": "normal",
        "position": {"x": 22.5, "y": 12.5}
      },
      {
        "name": "assembling-machine-1",
        "recipe": "copper-cable",
        "recipe_quality": "normal",
        "position": {"x": 22.5, "y": 15.5}
      },
      {
        "name": "assembling-machine-1",
        "recipe": "copper-cable",
        "recipe_quality": "normal",
        "position": {"x": 25.5, "y": 9.5}
      },
      {
        "name": "assembling-machine-1",
        "recipe": "copper-cable",
        "recipe_quality": "normal",
        "position": {"x": 28.5, "y": 9.5}
      },
      {
        "name": "assembling-machine-1",
        "recipe": "copper-cable",
        "recipe_quality": "normal",
        "position": {"x": 31.5, "y": 9.5}
      },
      {
        "name": "assembling-machine-1",
        "recipe": "copper-cable",
        "recipe_quality": "normal",
        "position": {"x": 25.5, "y": 12.5}
      },
      {
        "name": "assembling-machine-1",
        "recipe": "copper-cable",
        "recipe_quality": "normal",
        "position": {"x": 25.5, "y": 15.5}
      },
      {
        "name": "assembling-machine-1",
        "recipe": "copper-cable",
        "recipe_quality": "normal",
        "position": {"x": 28.5, "y": 12.5}
      },
      {
        "name": "assembling-machine-1",
        "recipe": "copper-cable",
        "recipe_quality": "normal",
        "position": {"x": 31.5, "y": 12.5}
      },
      {
        "name": "assembling-machine-1",
        "recipe": "copper-cable",
        "recipe_quality": "normal",
        "position": {"x": 28.5, "y": 15.5}
      },
      {
        "name": "assembling-machine-1",
        "recipe": "copper-cable",
        "recipe_quality": "normal",
        "position": {"x": 31.5, "y": 15.5}
      },
      {
        "name": "assembling-machine-1",
        "recipe": "copper-cable",
        "recipe_quality": "normal",
        "position": {"x": 22.5, "y": 18.5}
      },
      {
        "name": "assembling-machine-1",
        "recipe": "copper-cable",
        "recipe_quality": "normal",
        "position": {"x": 22.5, "y": 21.5}
      },
      {
        "name": "assembling-machine-1",
        "recipe": "copper-cable",
        "recipe_quality": "normal",
        "position": {"x": 25.5, "y": 18.5}
      },
      {
        "name": "assembling-machine-1",
        "recipe": "copper-cable",
        "recipe_quality": "normal",
        "position": {"x": 28.5, "y": 18.5}
      },
      {
        "name": "assembling-machine-1",
        "recipe": "copper-cable",
        "recipe_quality": "normal",
        "position": {"x": 31.5, "y": 18.5}
      },
      {
        "name": "assembling-machine-1",
        "recipe": "copper-cable",
        "recipe_quality": "normal",
        "position": {"x": 25.5, "y": 21.5}
      },
      {
        "name": "assembling-machine-1",
        "recipe": "copper-cable",
        "recipe_quality": "normal",
        "position": {"x": 28.5, "y": 21.5}
      },
      {
        "name": "assembling-machine-1",
        "recipe": "copper-cable",
        "recipe_quality": "normal",
        "position": {"x": 31.5, "y": 21.5}
      },
      {
        "name": "assembling-machine-1",
        "recipe": "copper-cable",
        "recipe_quality": "normal",
        "position": {"x": 22.5, "y": 24.5}
      },
      {
        "name": "assembling-machine-1",
        "recipe": "copper-cable",
        "recipe_quality": "normal",
        "position": {"x": 22.5, "y": 27.5}
      },
      {
        "name": "assembling-machine-1",
        "recipe": "copper-cable",
        "recipe_quality": "normal",
        "position": {"x": 25.5, "y": 24.5}
      },
      {
        "name": "assembling-machine-1",
        "recipe": "copper-cable",
        "recipe_quality": "normal",
        "position": {"x": 25.5, "y": 27.5}
      },
      {
        "name": "assembling-machine-1",
        "recipe": "copper-cable",
        "recipe_quality": "normal",
        "position": {"x": 28.5, "y": 24.5}
      },
      {
        "name": "assembling-machine-1",
        "recipe": "copper-cable",
        "recipe_quality": "normal",
        "position": {"x": 31.5, "y": 24.5}
      },
      {
        "name": "assembling-machine-1",
        "recipe": "copper-cable",
        "recipe_quality": "normal",
        "position": {"x": 28.5, "y": 27.5}
      },
      {
        "name": "assembling-machine-1",
        "recipe": "copper-cable",
        "recipe_quality": "normal",
        "position": {"x": 31.5, "y": 27.5}
      },
      {
        "name": "assembling-machine-1",
        "recipe": "electronic-circuit",
        "recipe_quality": "normal",
        "position": {"x": 34.5, "y": 6.5}
      },
      {
        "name": "assembling-machine-1",
        "recipe": "electronic-circuit",
        "recipe_quality": "normal",
        "position": {"x": 37.5, "y": 6.5}
      },
      {
        "name": "assembling-machine-1",
        "recipe": "electronic-circuit",
        "recipe_quality": "normal",
        "position": {"x": 34.5, "y": 9.5}
      },
      {
        "name": "assembling-machine-1",
        "recipe": "electronic-circuit",
        "recipe_quality": "normal",
        "position": {"x": 37.5, "y": 9.5}
      },
      {
        "name": "assembling-machine-1",
        "recipe": "electronic-circuit",
        "recipe_quality": "normal",
        "position": {"x": 34.5, "y": 12.5}
      },
      {
        "name": "assembling-machine-1",
        "recipe": "electronic-circuit",
        "recipe_quality": "normal",
        "position": {"x": 34.5, "y": 15.5}
      },
      {
        "name": "assembling-machine-1",
        "recipe": "electronic-circuit",
        "recipe_quality": "normal",
        "position": {"x": 37.5, "y": 12.5}
      },
      {
        "name": "assembling-machine-1",
        "recipe": "electronic-circuit",
        "recipe_quality": "normal",
        "position": {"x": 37.5, "y": 15.5}
      },
      {
        "name": "assembling-machine-1",
        "recipe": "engine-unit",
        "recipe_quality": "normal",
        "position": {"x": 61.5, "y": 0.5}
      },
      {
        "name": "assembling-machine-1",
        "recipe": "engine-unit",
        "recipe_quality": "normal",
        "position": {"x": 61.5, "y": 3.5}
      },
      {
        "name": "assembling-machine-1",
        "recipe": "engine-unit",
        "recipe_quality": "normal",
        "position": {"x": 61.5, "y": 6.5}
      },
      {
        "name": "assembling-machine-1",
        "recipe": "engine-unit",
        "recipe_quality": "normal",
        "position": {"x": 61.5, "y": 9.5}
      },
      {
        "name": "assembling-machine-1",
        "recipe": "engine-unit",
        "recipe_quality": "normal",
        "position": {"x": 61.5, "y": 12.5}
      },
      {
        "name": "assembling-machine-1",
        "recipe": "engine-unit",
        "recipe_quality": "normal",
        "position": {"x": 61.5, "y": 15.5}
      },
      {
        "name": "assembling-machine-1",
        "recipe": "electronic-circuit",
        "recipe_quality": "normal",
        "position": {"x": 34.5, "y": 18.5}
      },
      {
        "name": "assembling-machine-1",
        "recipe": "electronic-circuit",
        "recipe_quality": "normal",
        "position": {"x": 37.5, "y": 18.5}
      },
      {
        "name": "assembling-machine-1",
        "recipe": "electronic-circuit",
        "recipe_quality": "normal",
        "position": {"x": 34.5, "y": 21.5}
      },
      {
        "name": "assembling-machine-1",
        "recipe": "electronic-circuit",
        "recipe_quality": "normal",
        "position": {"x": 37.5, "y": 21.5}
      },
      {
        "name": "assembling-machine-1",
        "recipe": "electronic-circuit",
        "recipe_quality": "normal",
        "position": {"x": 34.5, "y": 24.5}
      },
      {
        "name": "assembling-machine-1",
        "recipe": "electronic-circuit",
        "recipe_quality": "normal",
        "position": {"x": 34.5, "y": 27.5}
      },
      {
        "name": "assembling-machine-1",
        "recipe": "electronic-circuit",
        "recipe_quality": "normal",
        "position": {"x": 37.5, "y": 24.5}
      },
      {
        "name": "assembling-machine-1",
        "recipe": "electronic-circuit",
        "recipe_quality": "normal",
        "position": {"x": 37.5, "y": 27.5}
      },
      {
        "name": "assembling-machine-1",
        "recipe": "pipe",
        "recipe_quality": "normal",
        "position": {"x": 55.5, "y": 18.5}
      },
      {
        "name": "assembling-machine-1",
        "recipe": "pipe",
        "recipe_quality": "normal",
        "position": {"x": 55.5, "y": 21.5}
      },
      {
        "name": "assembling-machine-1",
        "recipe": "engine-unit",
        "recipe_quality": "normal",
        "position": {"x": 61.5, "y": 18.5}
      },
      {
        "name": "assembling-machine-1",
        "recipe": "engine-unit",
        "recipe_quality": "normal",
        "position": {"x": 61.5, "y": 21.5}
      },
      {
        "name": "assembling-machine-1",
        "recipe": "pipe",
        "recipe_quality": "normal",
        "position": {"x": 55.5, "y": 24.5}
      },
      {
        "name": "assembling-machine-1",
        "recipe": "pipe",
        "recipe_quality": "normal",
        "position": {"x": 55.5, "y": 27.5}
      },
      {
        "name": "assembling-machine-1",
        "recipe": "iron-gear-wheel",
        "recipe_quality": "normal",
        "position": {"x": 58.5, "y": 24.5}
      },
      {
        "name": "assembling-machine-1",
        "recipe": "iron-gear-wheel",
        "recipe_quality": "normal",
        "position": {"x": 58.5, "y": 27.5}
      },
      {
        "name": "assembling-machine-1",
        "recipe": "engine-unit",
        "recipe_quality": "normal",
        "position": {"x": 61.5, "y": 24.5}
      },
      {
        "name": "assembling-machine-1",
        "recipe": "engine-unit",
        "recipe_quality": "normal",
        "position": {"x": 61.5, "y": 27.5}
      },
      {
        "name": "assembling-machine-1",
        "recipe": "engine-unit",
        "recipe_quality": "normal",
        "position": {"x": 64.5, "y": 0.5}
      },
      {
        "name": "assembling-machine-1",
        "recipe": "engine-unit",
        "recipe_quality": "normal",
        "position": {"x": 67.5, "y": 0.5}
      },
      {
        "name": "assembling-machine-1",
        "recipe": "engine-unit",
        "recipe_quality": "normal",
        "position": {"x": 64.5, "y": 3.5}
      },
      {
        "name": "assembling-machine-1",
        "recipe": "engine-unit",
        "recipe_quality": "normal",
        "position": {"x": 67.5, "y": 3.5}
      },
      {
        "name": "assembling-machine-1",
        "recipe": "engine-unit",
        "recipe_quality": "normal",
        "position": {"x": 70.5, "y": 0.5}
      },
      {
        "name": "assembling-machine-1",
        "recipe": "engine-unit",
        "recipe_quality": "normal",
        "position": {"x": 70.5, "y": 3.5}
      },
      {
        "name": "assembling-machine-1",
        "recipe": "engine-unit",
        "recipe_quality": "normal",
        "position": {"x": 64.5, "y": 6.5}
      },
      {
        "name": "assembling-machine-1",
        "recipe": "engine-unit",
        "recipe_quality": "normal",
        "position": {"x": 67.5, "y": 6.5}
      },
      {
        "name": "assembling-machine-1",
        "recipe": "engine-unit",
        "recipe_quality": "normal",
        "position": {"x": 70.5, "y": 6.5}
      },
      {
        "name": "assembling-machine-1",
        "recipe": "engine-unit",
        "recipe_quality": "normal",
        "position": {"x": 64.5, "y": 9.5}
      },
      {
        "name": "assembling-machine-1",
        "recipe": "engine-unit",
        "recipe_quality": "normal",
        "position": {"x": 67.5, "y": 9.5}
      },
      {
        "name": "assembling-machine-1",
        "recipe": "engine-unit",
        "recipe_quality": "normal",
        "position": {"x": 70.5, "y": 9.5}
      },
      {
        "name": "assembling-machine-1",
        "recipe": "engine-unit",
        "recipe_quality": "normal",
        "position": {"x": 64.5, "y": 12.5}
      },
      {
        "name": "assembling-machine-1",
        "recipe": "engine-unit",
        "recipe_quality": "normal",
        "position": {"x": 67.5, "y": 12.5}
      },
      {
        "name": "assembling-machine-1",
        "recipe": "engine-unit",
        "recipe_quality": "normal",
        "position": {"x": 64.5, "y": 15.5}
      },
      {
        "name": "assembling-machine-1",
        "recipe": "engine-unit",
        "recipe_quality": "normal",
        "position": {"x": 67.5, "y": 15.5}
      },
      {
        "name": "assembling-machine-1",
        "recipe": "engine-unit",
        "recipe_quality": "normal",
        "position": {"x": 70.5, "y": 12.5}
      },
      {
        "name": "assembling-machine-1",
        "recipe": "engine-unit",
        "recipe_quality": "normal",
        "position": {"x": 70.5, "y": 15.5}
      },
      {
        "name": "assembling-machine-1",
        "recipe": "flying-robot-frame",
        "recipe_quality": "normal",
        "position": {"x": 82.5, "y": 0.5}
      },
      {
        "name": "assembling-machine-1",
        "recipe": "flying-robot-frame",
        "recipe_quality": "normal",
        "position": {"x": 82.5, "y": 3.5}
      },
      {
        "name": "assembling-machine-1",
        "recipe": "flying-robot-frame",
        "recipe_quality": "normal",
        "position": {"x": 85.5, "y": 0.5}
      },
      {
        "name": "assembling-machine-1",
        "recipe": "flying-robot-frame",
        "recipe_quality": "normal",
        "position": {"x": 85.5, "y": 3.5}
      },
      {
        "name": "assembling-machine-1",
        "recipe": "flying-robot-frame",
        "recipe_quality": "normal",
        "position": {"x": 82.5, "y": 6.5}
      },
      {
        "name": "assembling-machine-1",
        "recipe": "flying-robot-frame",
        "recipe_quality": "normal",
        "position": {"x": 85.5, "y": 6.5}
      },
      {
        "name": "assembling-machine-1",
        "recipe": "flying-robot-frame",
        "recipe_quality": "normal",
        "position": {"x": 88.5, "y": 0.5}
      },
      {
        "name": "assembling-machine-1",
        "recipe": "flying-robot-frame",
        "recipe_quality": "normal",
        "position": {"x": 91.5, "y": 0.5}
      },
      {
        "name": "assembling-machine-1",
        "recipe": "flying-robot-frame",
        "recipe_quality": "normal",
        "position": {"x": 88.5, "y": 3.5}
      },
      {
        "name": "assembling-machine-1",
        "recipe": "flying-robot-frame",
        "recipe_quality": "normal",
        "position": {"x": 91.5, "y": 3.5}
      },
      {
        "name": "assembling-machine-1",
        "recipe": "flying-robot-frame",
        "recipe_quality": "normal",
        "position": {"x": 94.5, "y": 0.5}
      },
      {
        "name": "assembling-machine-1",
        "recipe": "flying-robot-frame",
        "recipe_quality": "normal",
        "position": {"x": 94.5, "y": 3.5}
      },
      {
        "name": "assembling-machine-1",
        "recipe": "flying-robot-frame",
        "recipe_quality": "normal",
        "position": {"x": 88.5, "y": 6.5}
      },
      {
        "name": "assembling-machine-1",
        "recipe": "flying-robot-frame",
        "recipe_quality": "normal",
        "position": {"x": 91.5, "y": 6.5}
      },
      {
        "name": "assembling-machine-1",
        "recipe": "flying-robot-frame",
        "recipe_quality": "normal",
        "position": {"x": 94.5, "y": 6.5}
      },
      {
        "name": "assembling-machine-1",
        "recipe": "flying-robot-frame",
        "recipe_quality": "normal",
        "position": {"x": 82.5, "y": 9.5}
      },
      {
        "name": "assembling-machine-1",
        "recipe": "flying-robot-frame",
        "recipe_quality": "normal",
        "position": {"x": 85.5, "y": 9.5}
      },
      {
        "name": "assembling-machine-1",
        "recipe": "flying-robot-frame",
        "recipe_quality": "normal",
        "position": {"x": 82.5, "y": 12.5}
      },
      {
        "name": "assembling-machine-1",
        "recipe": "flying-robot-frame",
        "recipe_quality": "normal",
        "position": {"x": 82.5, "y": 15.5}
      },
      {
        "name": "assembling-machine-1",
        "recipe": "flying-robot-frame",
        "recipe_quality": "normal",
        "position": {"x": 85.5, "y": 12.5}
      },
      {
        "name": "assembling-machine-1",
        "recipe": "flying-robot-frame",
        "recipe_quality": "normal",
        "position": {"x": 85.5, "y": 15.5}
      },
      {
        "name": "assembling-machine-1",
        "recipe": "flying-robot-frame",
        "recipe_quality": "normal",
        "position": {"x": 88.5, "y": 9.5}
      },
      {
        "name": "assembling-machine-1",
        "recipe": "flying-robot-frame",
        "recipe_quality": "normal",
        "position": {"x": 91.5, "y": 9.5}
      },
      {
        "name": "assembling-machine-1",
        "recipe": "flying-robot-frame",
        "recipe_quality": "normal",
        "position": {"x": 94.5, "y": 9.5}
      },
      {
        "name": "assembling-machine-1",
        "recipe": "flying-robot-frame",
        "recipe_quality": "normal",
        "position": {"x": 88.5, "y": 12.5}
      },
      {
        "name": "assembling-machine-1",
        "recipe": "flying-robot-frame",
        "recipe_quality": "normal",
        "position": {"x": 91.5, "y": 12.5}
      },
      {
        "name": "assembling-machine-1",
        "recipe": "flying-robot-frame",
        "recipe_quality": "normal",
        "position": {"x": 88.5, "y": 15.5}
      },
      {
        "name": "assembling-machine-1",
        "recipe": "flying-robot-frame",
        "recipe_quality": "normal",
        "position": {"x": 91.5, "y": 15.5}
      },
      {
        "name": "assembling-machine-1",
        "recipe": "flying-robot-frame",
        "recipe_quality": "normal",
        "position": {"x": 94.5, "y": 12.5}
      },
      {
        "name": "assembling-machine-1",
        "recipe": "flying-robot-frame",
        "recipe_quality": "normal",
        "position": {"x": 94.5, "y": 15.5}
      },
      {
        "name": "assembling-machine-1",
        "recipe": "engine-unit",
        "recipe_quality": "normal",
        "position": {"x": 64.5, "y": 18.5}
      },
      {
        "name": "assembling-machine-1",
        "recipe": "engine-unit",
        "recipe_quality": "normal",
        "position": {"x": 67.5, "y": 18.5}
      },
      {
        "name": "assembling-machine-1",
        "recipe": "engine-unit",
        "recipe_quality": "normal",
        "position": {"x": 70.5, "y": 18.5}
      },
      {
        "name": "assembling-machine-1",
        "recipe": "engine-unit",
        "recipe_quality": "normal",
        "position": {"x": 64.5, "y": 21.5}
      },
      {
        "name": "assembling-machine-1",
        "recipe": "engine-unit",
        "recipe_quality": "normal",
        "position": {"x": 67.5, "y": 21.5}
      },
      {
        "name": "assembling-machine-1",
        "recipe": "engine-unit",
        "recipe_quality": "normal",
        "position": {"x": 70.5, "y": 21.5}
      },
      {
        "name": "assembling-machine-1",
        "recipe": "engine-unit",
        "recipe_quality": "normal",
        "position": {"x": 64.5, "y": 24.5}
      },
      {
        "name": "assembling-machine-1",
        "recipe": "engine-unit",
        "recipe_quality": "normal",
        "position": {"x": 67.5, "y": 24.5}
      },
      {
        "name": "assembling-machine-1",
        "recipe": "engine-unit",
        "recipe_quality": "normal",
        "position": {"x": 64.5, "y": 27.5}
      },
      {
        "name": "assembling-machine-1",
        "recipe": "engine-unit",
        "recipe_quality": "normal",
        "position": {"x": 67.5, "y": 27.5}
      },
      {
        "name": "assembling-machine-1",
        "recipe": "engine-unit",
        "recipe_quality": "normal",
        "position": {"x": 70.5, "y": 24.5}
      },
      {
        "name": "assembling-machine-1",
        "recipe": "engine-unit",
        "recipe_quality": "normal",
        "position": {"x": 70.5, "y": 27.5}
      },
      {
        "name": "assembling-machine-1",
        "recipe": "flying-robot-frame",
        "recipe_quality": "normal",
        "position": {"x": 82.5, "y": 18.5}
      },
      {
        "name": "assembling-machine-1",
        "recipe": "flying-robot-frame",
        "recipe_quality": "normal",
        "position": {"x": 85.5, "y": 18.5}
      },
      {
        "name": "assembling-machine-1",
        "recipe": "flying-robot-frame",
        "recipe_quality": "normal",
        "position": {"x": 82.5, "y": 21.5}
      },
      {
        "name": "assembling-machine-1",
        "recipe": "flying-robot-frame",
        "recipe_quality": "normal",
        "position": {"x": 85.5, "y": 21.5}
      },
      {
        "name": "assembling-machine-1",
        "recipe": "flying-robot-frame",
        "recipe_quality": "normal",
        "position": {"x": 88.5, "y": 18.5}
      },
      {
        "name": "assembling-machine-1",
        "recipe": "flying-robot-frame",
        "recipe_quality": "normal",
        "position": {"x": 91.5, "y": 18.5}
      },
      {
        "name": "assembling-machine-1",
        "recipe": "flying-robot-frame",
        "recipe_quality": "normal",
        "position": {"x": 94.5, "y": 18.5}
      },
      {
        "name": "assembling-machine-1",
        "recipe": "flying-robot-frame",
        "recipe_quality": "normal",
        "position": {"x": 88.5, "y": 21.5}
      },
      {
        "name": "assembling-machine-1",
        "recipe": "flying-robot-frame",
        "recipe_quality": "normal",
        "position": {"x": 91.5, "y": 21.5}
      },
      {
        "name": "assembling-machine-1",
        "recipe": "flying-robot-frame",
        "recipe_quality": "normal",
        "position": {"x": 94.5, "y": 21.5}
      },
      {
        "name": "assembling-machine-1",
        "recipe": "flying-robot-frame",
        "recipe_quality": "normal",
        "position": {"x": 82.5, "y": 24.5}
      },
      {
        "name": "assembling-machine-1",
        "recipe": "flying-robot-frame",
        "recipe_quality": "normal",
        "position": {"x": 82.5, "y": 27.5}
      },
      {
        "name": "assembling-machine-1",
        "recipe": "flying-robot-frame",
        "recipe_quality": "normal",
        "position": {"x": 85.5, "y": 24.5}
      },
      {
        "name": "assembling-machine-1",
        "recipe": "flying-robot-frame",
        "recipe_quality": "normal",
        "position": {"x": 85.5, "y": 27.5}
      },
      {
        "name": "assembling-machine-1",
        "recipe": "flying-robot-frame",
        "recipe_quality": "normal",
        "position": {"x": 88.5, "y": 24.5}
      },
      {
        "name": "assembling-machine-1",
        "recipe": "flying-robot-frame",
        "recipe_quality": "normal",
        "position": {"x": 91.5, "y": 24.5}
      },
      {
        "name": "assembling-machine-1",
        "recipe": "flying-robot-frame",
        "recipe_quality": "normal",
        "position": {"x": 88.5, "y": 27.5}
      },
      {
        "name": "assembling-machine-1",
        "recipe": "flying-robot-frame",
        "recipe_quality": "normal",
        "position": {"x": 91.5, "y": 27.5}
      },
      {
        "name": "assembling-machine-1",
        "recipe": "flying-robot-frame",
        "recipe_quality": "normal",
        "position": {"x": 94.5, "y": 24.5}
      },
      {
        "name": "assembling-machine-1",
        "recipe": "flying-robot-frame",
        "recipe_quality": "normal",
        "position": {"x": 94.5, "y": 27.5}
      },
      {
        "name": "assembling-machine-1",
        "recipe": "flying-robot-frame",
        "recipe_quality": "normal",
        "position": {"x": 97.5, "y": 0.5}
      },
      {
        "name": "assembling-machine-1",
        "recipe": "flying-robot-frame",
        "recipe_quality": "normal",
        "position": {"x": 97.5, "y": 3.5}
      },
      {
        "name": "assembling-machine-1",
        "recipe": "flying-robot-frame",
        "recipe_quality": "normal",
        "position": {"x": 100.5, "y": 0.5}
      },
      {
        "name": "assembling-machine-1",
        "recipe": "flying-robot-frame",
        "recipe_quality": "normal",
        "position": {"x": 103.5, "y": 0.5}
      },
      {
        "name": "assembling-machine-1",
        "recipe": "flying-robot-frame",
        "recipe_quality": "normal",
        "position": {"x": 100.5, "y": 3.5}
      },
      {
        "name": "assembling-machine-1",
        "recipe": "flying-robot-frame",
        "recipe_quality": "normal",
        "position": {"x": 103.5, "y": 3.5}
      },
      {
        "name": "assembling-machine-1",
        "recipe": "flying-robot-frame",
        "recipe_quality": "normal",
        "position": {"x": 97.5, "y": 6.5}
      },
      {
        "name": "assembling-machine-1",
        "recipe": "flying-robot-frame",
        "recipe_quality": "normal",
        "position": {"x": 100.5, "y": 6.5}
      },
      {
        "name": "assembling-machine-1",
        "recipe": "flying-robot-frame",
        "recipe_quality": "normal",
        "position": {"x": 103.5, "y": 6.5}
      },
      {
        "name": "assembling-machine-1",
        "recipe": "advanced-circuit",
        "recipe_quality": "normal",
        "position": {"x": 109.5, "y": 6.5}
      },
      {
        "name": "assembling-machine-1",
        "recipe": "flying-robot-frame",
        "recipe_quality": "normal",
        "position": {"x": 97.5, "y": 9.5}
      },
      {
        "name": "assembling-machine-1",
        "recipe": "flying-robot-frame",
        "recipe_quality": "normal",
        "position": {"x": 100.5, "y": 9.5}
      },
      {
        "name": "assembling-machine-1",
        "recipe": "flying-robot-frame",
        "recipe_quality": "normal",
        "position": {"x": 103.5, "y": 9.5}
      },
      {
        "name": "assembling-machine-1",
        "recipe": "flying-robot-frame",
        "recipe_quality": "normal",
        "position": {"x": 97.5, "y": 12.5}
      },
      {
        "name": "assembling-machine-1",
        "recipe": "flying-robot-frame",
        "recipe_quality": "normal",
        "position": {"x": 97.5, "y": 15.5}
      },
      {
        "name": "assembling-machine-1",
        "recipe": "flying-robot-frame",
        "recipe_quality": "normal",
        "position": {"x": 100.5, "y": 12.5}
      },
      {
        "name": "assembling-machine-1",
        "recipe": "flying-robot-frame",
        "recipe_quality": "normal",
        "position": {"x": 103.5, "y": 12.5}
      },
      {
        "name": "assembling-machine-1",
        "recipe": "flying-robot-frame",
        "recipe_quality": "normal",
        "position": {"x": 100.5, "y": 15.5}
      },
      {
        "name": "assembling-machine-1",
        "recipe": "flying-robot-frame",
        "recipe_quality": "normal",
        "position": {"x": 103.5, "y": 15.5}
      },
      {
        "name": "assembling-machine-1",
        "recipe": "advanced-circuit",
        "recipe_quality": "normal",
        "position": {"x": 109.5, "y": 9.5}
      },
      {
        "name": "assembling-machine-1",
        "recipe": "advanced-circuit",
        "recipe_quality": "normal",
        "position": {"x": 109.5, "y": 12.5}
      },
      {
        "name": "assembling-machine-1",
        "recipe": "advanced-circuit",
        "recipe_quality": "normal",
        "position": {"x": 109.5, "y": 15.5}
      },
      {
        "name": "assembling-machine-1",
        "recipe": "advanced-circuit",
        "recipe_quality": "normal",
        "position": {"x": 112.5, "y": 6.5}
      },
      {
        "name": "assembling-machine-1",
        "recipe": "advanced-circuit",
        "recipe_quality": "normal",
        "position": {"x": 115.5, "y": 6.5}
      },
      {
        "name": "assembling-machine-1",
        "recipe": "advanced-circuit",
        "recipe_quality": "normal",
        "position": {"x": 112.5, "y": 9.5}
      },
      {
        "name": "assembling-machine-1",
        "recipe": "advanced-circuit",
        "recipe_quality": "normal",
        "position": {"x": 115.5, "y": 9.5}
      },
      {
        "name": "assembling-machine-1",
        "recipe": "advanced-circuit",
        "recipe_quality": "normal",
        "position": {"x": 112.5, "y": 12.5}
      },
      {
        "name": "assembling-machine-1",
        "recipe": "advanced-circuit",
        "recipe_quality": "normal",
        "position": {"x": 115.5, "y": 12.5}
      },
      {
        "name": "assembling-machine-1",
        "recipe": "advanced-circuit",
        "recipe_quality": "normal",
        "position": {"x": 112.5, "y": 15.5}
      },
      {
        "name": "assembling-machine-1",
        "recipe": "advanced-circuit",
        "recipe_quality": "normal",
        "position": {"x": 115.5, "y": 15.5}
      },
      {
        "name": "assembling-machine-1",
        "recipe": "flying-robot-frame",
        "recipe_quality": "normal",
        "position": {"x": 97.5, "y": 18.5}
      },
      {
        "name": "assembling-machine-1",
        "recipe": "flying-robot-frame",
        "recipe_quality": "normal",
        "position": {"x": 100.5, "y": 18.5}
      },
      {
        "name": "assembling-machine-1",
        "recipe": "flying-robot-frame",
        "recipe_quality": "normal",
        "position": {"x": 103.5, "y": 18.5}
      },
      {
        "name": "assembling-machine-1",
        "recipe": "flying-robot-frame",
        "recipe_quality": "normal",
        "position": {"x": 97.5, "y": 21.5}
      },
      {
        "name": "assembling-machine-1",
        "recipe": "flying-robot-frame",
        "recipe_quality": "normal",
        "position": {"x": 100.5, "y": 21.5}
      },
      {
        "name": "assembling-machine-1",
        "recipe": "flying-robot-frame",
        "recipe_quality": "normal",
        "position": {"x": 103.5, "y": 21.5}
      },
      {
        "name": "assembling-machine-1",
        "recipe": "advanced-circuit",
        "recipe_quality": "normal",
        "position": {"x": 109.5, "y": 18.5}
      },
      {
        "name": "assembling-machine-1",
        "recipe": "advanced-circuit",
        "recipe_quality": "normal",
        "position": {"x": 109.5, "y": 21.5}
      },
      {
        "name": "assembling-machine-1",
        "recipe": "flying-robot-frame",
        "recipe_quality": "normal",
        "position": {"x": 97.5, "y": 24.5}
      },
      {
        "name": "assembling-machine-1",
        "recipe": "flying-robot-frame",
        "recipe_quality": "normal",
        "position": {"x": 97.5, "y": 27.5}
      },
      {
        "name": "assembling-machine-1",
        "recipe": "flying-robot-frame",
        "recipe_quality": "normal",
        "position": {"x": 100.5, "y": 24.5}
      },
      {
        "name": "assembling-machine-1",
        "recipe": "flying-robot-frame",
        "recipe_quality": "normal",
        "position": {"x": 103.5, "y": 24.5}
      },
      {
        "name": "assembling-machine-1",
        "recipe": "flying-robot-frame",
        "recipe_quality": "normal",
        "position": {"x": 100.5, "y": 27.5}
      },
      {
        "name": "assembling-machine-1",
        "recipe": "flying-robot-frame",
        "recipe_quality": "normal",
        "position": {"x": 103.5, "y": 27.5}
      },
      {
        "name": "assembling-machine-1",
        "recipe": "advanced-circuit",
        "recipe_quality": "normal",
        "position": {"x": 109.5, "y": 24.5}
      },
      {
        "name": "assembling-machine-1",
        "recipe": "advanced-circuit",
        "recipe_quality": "normal",
        "position": {"x": 109.5, "y": 27.5}
      },
      {
        "name": "assembling-machine-1",
        "recipe": "advanced-circuit",
        "recipe_quality": "normal",
        "position": {"x": 112.5, "y": 18.5}
      },
      {
        "name": "assembling-machine-1",
        "recipe": "advanced-circuit",
        "recipe_quality": "normal",
        "position": {"x": 115.5, "y": 18.5}
      },
      {
        "name": "assembling-machine-1",
        "recipe": "advanced-circuit",
        "recipe_quality": "normal",
        "position": {"x": 112.5, "y": 21.5}
      },
      {
        "name": "assembling-machine-1",
        "recipe": "advanced-circuit",
        "recipe_quality": "normal",
        "position": {"x": 115.5, "y": 21.5}
      },
      {
        "name": "assembling-machine-1",
        "recipe": "advanced-circuit",
        "recipe_quality": "normal",
        "position": {"x": 112.5, "y": 24.5}
      },
      {
        "name": "assembling-machine-1",
        "recipe": "advanced-circuit",
        "recipe_quality": "normal",
        "position": {"x": 115.5, "y": 24.5}
      },
      {
        "name": "assembling-machine-1",
        "recipe": "advanced-circuit",
        "recipe_quality": "normal",
        "position": {"x": 112.5, "y": 27.5}
      },
      {
        "name": "assembling-machine-1",
        "recipe": "advanced-circuit",
        "recipe_quality": "normal",
        "position": {"x": 115.5, "y": 27.5}
      },
      {
        "name": "assembling-machine-1",
        "recipe": "construction-robot",
        "recipe_quality": "normal",
        "position": {"x": 118.5, "y": 27.5}
      },
      {
        "name": "assembling-machine-1",
        "recipe": "logistic-robot",
        "recipe_quality": "normal",
        "position": {"x": 121.5, "y": 27.5}
      },
      {
        "name": "assembling-machine-2",
        "recipe": "electric-engine-unit",
        "recipe_quality": "normal",
        "position": {"x": 73.5, "y": 3.5}
      },
      {
        "name": "assembling-machine-2",
        "recipe": "electric-engine-unit",
        "recipe_quality": "normal",
        "position": {"x": 76.5, "y": 3.5}
      },
      {
        "name": "assembling-machine-2",
        "recipe": "electric-engine-unit",
        "recipe_quality": "normal",
        "position": {"x": 79.5, "y": 3.5}
      },
      {
        "name": "assembling-machine-2",
        "recipe": "electric-engine-unit",
        "recipe_quality": "normal",
        "position": {"x": 73.5, "y": 6.5}
      },
      {
        "name": "assembling-machine-2",
        "recipe": "electric-engine-unit",
        "recipe_quality": "normal",
        "position": {"x": 76.5, "y": 6.5}
      },
      {
        "name": "assembling-machine-2",
        "recipe": "electric-engine-unit",
        "recipe_quality": "normal",
        "position": {"x": 79.5, "y": 6.5}
      },
      {
        "name": "assembling-machine-2",
        "recipe": "electric-engine-unit",
        "recipe_quality": "normal",
        "position": {"x": 73.5, "y": 9.5}
      },
      {
        "name": "assembling-machine-2",
        "recipe": "electric-engine-unit",
        "recipe_quality": "normal",
        "position": {"x": 76.5, "y": 9.5}
      },
      {
        "name": "assembling-machine-2",
        "recipe": "electric-engine-unit",
        "recipe_quality": "normal",
        "position": {"x": 79.5, "y": 9.5}
      },
      {
        "name": "assembling-machine-2",
        "recipe": "electric-engine-unit",
        "recipe_quality": "normal",
        "position": {"x": 73.5, "y": 12.5}
      },
      {
        "name": "assembling-machine-2",
        "recipe": "electric-engine-unit",
        "recipe_quality": "normal",
        "position": {"x": 73.5, "y": 15.5}
      },
      {
        "name": "assembling-machine-2",
        "recipe": "electric-engine-unit",
        "recipe_quality": "normal",
        "position": {"x": 76.5, "y": 12.5}
      },
      {
        "name": "assembling-machine-2",
        "recipe": "electric-engine-unit",
        "recipe_quality": "normal",
        "position": {"x": 79.5, "y": 12.5}
      },
      {
        "name": "assembling-machine-2",
        "recipe": "electric-engine-unit",
        "recipe_quality": "normal",
        "position": {"x": 76.5, "y": 15.5}
      },
      {
        "name": "assembling-machine-2",
        "recipe": "electric-engine-unit",
        "recipe_quality": "normal",
        "position": {"x": 79.5, "y": 15.5}
      },
      {
        "name": "assembling-machine-2",
        "recipe": "electric-engine-unit",
        "recipe_quality": "normal",
        "position": {"x": 73.5, "y": 18.5}
      },
      {
        "name": "assembling-machine-2",
        "recipe": "electric-engine-unit",
        "recipe_quality": "normal",
        "position": {"x": 76.5, "y": 18.5}
      },
      {
        "name": "assembling-machine-2",
        "recipe": "electric-engine-unit",
        "recipe_quality": "normal",
        "position": {"x": 79.5, "y": 18.5}
      },
      {
        "name": "assembling-machine-2",
        "recipe": "electric-engine-unit",
        "recipe_quality": "normal",
        "position": {"x": 73.5, "y": 21.5}
      },
      {
        "name": "assembling-machine-2",
        "recipe": "electric-engine-unit",
        "recipe_quality": "normal",
        "position": {"x": 76.5, "y": 21.5}
      },
      {
        "name": "assembling-machine-2",
        "recipe": "electric-engine-unit",
        "recipe_quality": "normal",
        "position": {"x": 79.5, "y": 21.5}
      },
      {
        "name": "assembling-machine-2",
        "recipe": "electric-engine-unit",
        "recipe_quality": "normal",
        "position": {"x": 73.5, "y": 24.5}
      },
      {
        "name": "assembling-machine-2",
        "recipe": "electric-engine-unit",
        "recipe_quality": "normal",
        "position": {"x": 73.5, "y": 27.5}
      },
      {
        "name": "assembling-machine-2",
        "recipe": "electric-engine-unit",
        "recipe_quality": "normal",
        "position": {"x": 76.5, "y": 24.5}
      },
      {
        "name": "assembling-machine-2",
        "recipe": "electric-engine-unit",
        "recipe_quality": "normal",
        "position": {"x": 79.5, "y": 24.5}
      },
      {
        "name": "assembling-machine-2",
        "recipe": "electric-engine-unit",
        "recipe_quality": "normal",
        "position": {"x": 76.5, "y": 27.5}
      },
      {
        "name": "assembling-machine-2",
        "recipe": "electric-engine-unit",
        "recipe_quality": "normal",
        "position": {"x": 79.5, "y": 27.5}
      },
      {
        "name": "chemical-plant",
        "direction": 4,
        "recipe": "light-oil-cracking",
        "recipe_quality": "normal",
        "position": {"x": 11.5, "y": 9.5}
      },
      {
        "name": "chemical-plant",
        "direction": 4,
        "recipe": "light-oil-cracking",
        "recipe_quality": "normal",
        "position": {"x": 11.5, "y": 12.5}
      },
      {
        "name": "chemical-plant",
        "direction": 4,
        "recipe": "light-oil-cracking",
        "recipe_quality": "normal",
        "position": {"x": 11.5, "y": 15.5}
      },
      {
        "name": "chemical-plant",
        "direction": 4,
        "recipe": "light-oil-cracking",
        "recipe_quality": "normal",
        "position": {"x": 11.5, "y": 18.5}
      },
      {
        "name": "chemical-plant",
        "direction": 4,
        "recipe": "light-oil-cracking",
        "recipe_quality": "normal",
        "position": {"x": 11.5, "y": 21.5}
      },
      {
        "name": "chemical-plant",
        "direction": 4,
        "recipe": "light-oil-cracking",
        "recipe_quality": "normal",
        "position": {"x": 11.5, "y": 24.5}
      },
      {
        "name": "chemical-plant",
        "direction": 4,
        "recipe": "light-oil-cracking",
        "recipe_quality": "normal",
        "position": {"x": 11.5, "y": 27.5}
      },
      {
        "name": "chemical-plant",
        "direction": 4,
        "recipe": "heavy-oil-cracking",
        "recipe_quality": "normal",
        "position": {"x": 14.5, "y": 27.5}
      },
      {
        "name": "chemical-plant",
        "direction": 4,
        "recipe": "battery",
        "recipe_quality": "normal",
        "position": {"x": 46.5, "y": 6.5}
      },
      {
        "name": "chemical-plant",
        "direction": 4,
        "recipe": "battery",
        "recipe_quality": "normal",
        "position": {"x": 46.5, "y": 9.5}
      },
      {
        "name": "chemical-plant",
        "direction": 4,
        "recipe": "battery",
        "recipe_quality": "normal",
        "position": {"x": 46.5, "y": 12.5}
      },
      {
        "name": "chemical-plant",
        "direction": 4,
        "recipe": "battery",
        "recipe_quality": "normal",
        "position": {"x": 46.5, "y": 15.5}
      },
      {
        "name": "chemical-plant",
        "direction": 4,
        "recipe": "battery",
        "recipe_quality": "normal",
        "position": {"x": 49.5, "y": 6.5}
      },
      {
        "name": "chemical-plant",
        "direction": 4,
        "recipe": "battery",
        "recipe_quality": "normal",
        "position": {"x": 49.5, "y": 9.5}
      },
      {
        "name": "chemical-plant",
        "direction": 4,
        "recipe": "battery",
        "recipe_quality": "normal",
        "position": {"x": 49.5, "y": 12.5}
      },
      {
        "name": "chemical-plant",
        "direction": 4,
        "recipe": "battery",
        "recipe_quality": "normal",
        "position": {"x": 49.5, "y": 15.5}
      },
      {
        "name": "chemical-plant",
        "direction": 4,
        "recipe": "sulfur",
        "recipe_quality": "normal",
        "position": {"x": 40.5, "y": 18.5}
      },
      {
        "name": "chemical-plant",
        "direction": 4,
        "recipe": "battery",
        "recipe_quality": "normal",
        "position": {"x": 46.5, "y": 18.5}
      },
      {
        "name": "chemical-plant",
        "direction": 4,
        "recipe": "sulfur",
        "recipe_quality": "normal",
        "position": {"x": 40.5, "y": 21.5}
      },
      {
        "name": "chemical-plant",
        "direction": 4,
        "recipe": "battery",
        "recipe_quality": "normal",
        "position": {"x": 46.5, "y": 21.5}
      },
      {
        "name": "chemical-plant",
        "direction": 4,
        "recipe": "sulfur",
        "recipe_quality": "normal",
        "position": {"x": 40.5, "y": 24.5}
      },
      {
        "name": "chemical-plant",
        "direction": 4,
        "recipe": "sulfuric-acid",
        "recipe_quality": "normal",
        "position": {"x": 43.5, "y": 24.5}
      },
      {
        "name": "chemical-plant",
        "direction": 4,
        "recipe": "sulfur",
        "recipe_quality": "normal",
        "position": {"x": 40.5, "y": 27.5}
      },
      {
        "name": "chemical-plant",
        "direction": 4,
        "recipe": "sulfuric-acid",
        "recipe_quality": "normal",
        "position": {"x": 43.5, "y": 27.5}
      },
      {
        "name": "chemical-plant",
        "direction": 4,
        "recipe": "battery",
        "recipe_quality": "normal",
        "position": {"x": 46.5, "y": 24.5}
      },
      {
        "name": "chemical-plant",
        "direction": 4,
        "recipe": "battery",
        "recipe_quality": "normal",
        "position": {"x": 46.5, "y": 27.5}
      },
      {
        "name": "chemical-plant",
        "direction": 4,
        "recipe": "battery",
        "recipe_quality": "normal",
        "position": {"x": 49.5, "y": 18.5}
      },
      {
        "name": "chemical-plant",
        "direction": 4,
        "recipe": "battery",
        "recipe_quality": "normal",
        "position": {"x": 49.5, "y": 21.5}
      },
      {
        "name": "chemical-plant",
        "direction": 4,
        "recipe": "lubricant",
        "recipe_quality": "normal",
        "position": {"x": 52.5, "y": 21.5}
      },
      {
        "name": "chemical-plant",
        "direction": 4,
        "recipe": "battery",
        "recipe_quality": "normal",
        "position": {"x": 49.5, "y": 24.5}
      },
      {
        "name": "chemical-plant",
        "direction": 4,
        "recipe": "battery",
        "recipe_quality": "normal",
        "position": {"x": 49.5, "y": 27.5}
      },
      {
        "name": "chemical-plant",
        "direction": 4,
        "recipe": "lubricant",
        "recipe_quality": "normal",
        "position": {"x": 52.5, "y": 24.5}
      },
      {
        "name": "chemical-plant",
        "direction": 4,
        "recipe": "lubricant",
        "recipe_quality": "normal",
        "position": {"x": 52.5, "y": 27.5}
      },
      {
        "name": "chemical-plant",
        "direction": 4,
        "recipe": "plastic-bar",
        "recipe_quality": "normal",
        "position": {"x": 106.5, "y": 24.5}
      },
      {
        "name": "chemical-plant",
        "direction": 4,
        "recipe": "plastic-bar",
        "recipe_quality": "normal",
        "position": {"x": 106.5, "y": 27.5}
      },
      {"name": "electric-furnace", "position": {"x": -0.5, "y": 6.5}},
      {"name": "electric-furnace", "position": {"x": -0.5, "y": 9.5}},
      {"name": "electric-furnace", "position": {"x": -0.5, "y": 12.5}},
      {"name": "electric-furnace", "position": {"x": -0.5, "y": 15.5}},
      {"name": "electric-furnace", "position": {"x": -0.5, "y": 18.5}},
      {"name": "electric-furnace", "position": {"x": -0.5, "y": 21.5}},
      {"name": "electric-furnace", "position": {"x": -0.5, "y": 24.5}},
      {"name": "electric-furnace", "position": {"x": -0.5, "y": 27.5}},
      {"name": "electric-furnace", "position": {"x": 2.5, "y": 6.5}},
      {"name": "electric-furnace", "position": {"x": 5.5, "y": 6.5}},
      {"name": "electric-furnace", "position": {"x": 8.5, "y": 6.5}},
      {"name": "electric-furnace", "position": {"x": 2.5, "y": 9.5}},
      {"name": "electric-furnace", "position": {"x": 5.5, "y": 9.5}},
      {"name": "electric-furnace", "position": {"x": 2.5, "y": 12.5}},
      {"name": "electric-furnace", "position": {"x": 2.5, "y": 15.5}},
      {"name": "electric-furnace", "position": {"x": 5.5, "y": 12.5}},
      {"name": "electric-furnace", "position": {"x": 5.5, "y": 15.5}},
      {"name": "electric-furnace", "position": {"x": 8.5, "y": 9.5}},
      {"name": "electric-furnace", "position": {"x": 8.5, "y": 12.5}},
      {"name": "electric-furnace", "position": {"x": 8.5, "y": 15.5}},
      {"name": "electric-furnace", "position": {"x": 2.5, "y": 18.5}},
      {"name": "electric-furnace", "position": {"x": 5.5, "y": 18.5}},
      {"name": "electric-furnace", "position": {"x": 2.5, "y": 21.5}},
      {"name": "electric-furnace", "position": {"x": 5.5, "y": 21.5}},
      {"name": "electric-furnace", "position": {"x": 8.5, "y": 18.5}},
      {"name": "electric-furnace", "position": {"x": 8.5, "y": 21.5}},
      {"name": "electric-furnace", "position": {"x": 2.5, "y": 24.5}},
      {"name": "electric-furnace", "position": {"x": 2.5, "y": 27.5}},
      {"name": "electric-furnace", "position": {"x": 5.5, "y": 24.5}},
      {"name": "electric-furnace", "position": {"x": 5.5, "y": 27.5}},
      {"name": "electric-furnace", "position": {"x": 8.5, "y": 24.5}},
      {"name": "electric-furnace", "position": {"x": 8.5, "y": 27.5}},
      {
        "name": "oil-refinery",
        "direction": 4,
        "recipe": "advanced-oil-processing",
        "recipe_quality": "normal",
        "position": {"x": 18.5, "y": -13.5}
      },
      {
        "name": "oil-refinery",
        "direction": 4,
        "recipe": "advanced-oil-processing",
        "recipe_quality": "normal",
        "position": {"x": 18.5, "y": -8.5}
      },
      {
        "name": "oil-refinery",
        "direction": 4,
        "recipe": "advanced-oil-processing",
        "recipe_quality": "normal",
        "position": {"x": 18.5, "y": -3.5}
      },
      {
        "name": "oil-refinery",
        "direction": 4,
        "recipe": "advanced-oil-processing",
        "recipe_quality": "normal",
        "position": {"x": 18.5, "y": 1.5}
      },
      {
        "name": "oil-refinery",
        "direction": 4,
        "recipe": "advanced-oil-processing",
        "recipe_quality": "normal",
        "position": {"x": 18.5, "y": 6.5}
      },
      {
        "name": "oil-refinery",
        "direction": 4,
        "recipe": "advanced-oil-processing",
        "recipe_quality": "normal",
        "position": {"x": 18.5, "y": 11.5}
      },
      {
        "name": "oil-refinery",
        "direction": 4,
        "recipe": "advanced-oil-processing",
        "recipe_quality": "normal",
        "position": {"x": 18.5, "y": 16.5}
      },
      {
        "name": "oil-refinery",
        "direction": 4,
        "recipe": "advanced-oil-processing",
        "recipe_quality": "normal",
        "position": {"x": 18.5, "y": 21.5}
      },
      {
        "name": "oil-refinery",
        "direction": 4,
        "recipe": "advanced-oil-processing",
        "recipe_quality": "normal",
        "position": {"x": 18.5, "y": 26.5}
      }
    ],
    "icons": [
      {"index": 1, "signal": {"name": "logistic-robot"}},
      {"index": 2, "signal": {"name": "construction-robot"}}
    ]
  }
}
