{
  "index": 8,
  "blueprint": {
    "item": "blueprint",
    "label": "Early game manual load defense",
    "shift_x": -104,
    "shift_y": 214,
    "version": 562949956108288,
    "entities": [
      {
        "name": "assembling-machine-1",
        "recipe": "firearm-magazine",
        "recipe_quality": "normal",
        "position": {"x": -0.5, "y": 0.5}
      },
      {
        "name": "assembling-machine-1",
        "recipe": "pipe",
        "recipe_quality": "normal",
        "position": {"x": -3.5, "y": 2.5}
      },
      {
        "name": "assembling-machine-1",
        "recipe": "firearm-magazine",
        "recipe_quality": "normal",
        "position": {"x": -0.5, "y": 4.5}
      },
      {
        "name": "assembling-machine-1",
        "recipe": "firearm-magazine",
        "recipe_quality": "normal",
        "position": {"x": 2.5, "y": 0.5}
      },
      {
        "name": "assembling-machine-1",
        "recipe": "gun-turret",
        "recipe_quality": "normal",
        "position": {"x": 5.5, "y": 0.5}
      },
      {
        "name": "assembling-machine-1",
        "recipe": "firearm-magazine",
        "recipe_quality": "normal",
        "position": {"x": 2.5, "y": 4.5}
      },
      {
        "name": "assembling-machine-1",
        "recipe": "gun-turret",
        "recipe_quality": "normal",
        "position": {"x": 5.5, "y": 4.5}
      },
      {
        "name": "assembling-machine-1",
        "recipe": "iron-gear-wheel",
        "recipe_quality": "normal",
        "position": {"x": 9.5, "y": 2.5}
      },
      {"name": "inserter", "direction": 4, "position": {"x": 7.5, "y": 1.5}},
      {"name": "inserter", "direction": 4, "position": {"x": 7.5, "y": 3.5}},
      {"name": "small-electric-pole", "position": {"x": -0.5, "y": 2.5}},
      {"name": "small-electric-pole", "position": {"x": 6.5, "y": 2.5}}
    ],
    "icons": [
      {"index": 1, "signal": {"name": "gun-turret"}},
      {"index": 2, "signal": {"name": "firearm-magazine"}},
      {"index": 3, "signal": {"name": "pipe"}}
    ],
    "wires": [["3,2", 5, "10,2", 5]]
  }
}
